utils/__init__.py
utils/features.py
kgf-0.1.dist-info/METADATA
kgf-0.1.dist-info/WHEEL
kgf-0.1.dist-info/top_level.txt
kgf-0.1.dist-info/RECORD
